LICENSE
MANIFEST.in
README.md
requirements.txt
setup.py
rtlsdr_nfs32002/protocol.py
rtlsdr_nfs32002/utils.py
rtlsdr_nfs32002.egg-info/PKG-INFO
rtlsdr_nfs32002.egg-info/SOURCES.txt
rtlsdr_nfs32002.egg-info/dependency_links.txt
rtlsdr_nfs32002.egg-info/requires.txt
rtlsdr_nfs32002.egg-info/top_level.txt