Metadata-Version: 2.1
Name: rtlsdr-nfs32002
Version: 0.2
Summary: Réimplémentation du protocole NF S 32002 utilisé par les balises sonores des feux piétons. Permet de détecter le signal d'une télécommande à partir d'un RTL SDR.
Home-page: https://github.com/balises-ouistici/rtlsdr_nfs32002
Author: Jérémy Kalsron
Author-email: jeremy.kalsron@gmail.com  
License: AGPL-3.0
Classifier: License :: OSI Approved :: GNU Affero General Public License v3 or later (AGPLv3+)
Classifier: Programming Language :: Python :: 3
Classifier: Programming Language :: Python :: 3.7
License-File: LICENSE
